typing_copilot/__init__.py
typing_copilot/__main__.py
typing_copilot/cli.py
typing_copilot/config_generation.py
typing_copilot/error_tracker.py
typing_copilot/mypy_runner.py
typing_copilot/own_config.py
typing_copilot/validation.py
typing_copilot/verbosity.py
typing_copilot/tests/__init__.py
typing_copilot/tests/test_config_generation.py
typing_copilot/tests/test_own_config.py
typing_copilot-0.7.0.dist-info/LICENSE
typing_copilot-0.7.0.dist-info/METADATA
typing_copilot-0.7.0.dist-info/WHEEL
typing_copilot-0.7.0.dist-info/entry_points.txt
typing_copilot-0.7.0.dist-info/top_level.txt
typing_copilot-0.7.0.dist-info/RECORD
