Metadata-Version: 2.1
Name: typing-copilot
Version: 0.7.0
Summary: Helper for starting to type-hint large codebases with mypy.
Home-page: https://github.com/obi1kenobi/typing-copilot
Author: Predrag Gruevski
Author-email: obi1kenobi82@gmail.com
License: MIT
Platform: UNKNOWN
Requires-Python: >=3.7
License-File: LICENSE
Requires-Dist: click (<9,>=8)
Requires-Dist: mypy (>=0.782)
Requires-Dist: toml (<1,>=0.10.2)
Requires-Dist: types-toml (<1,>=0.10.4)
